CHANGES.rst
LICENSE.rst
feedback_form/__init__.py
feedback_form/apps.py
feedback_form/conf.py
feedback_form/forms.py
feedback_form/migrations/__init__.py
feedback_form/templates/feedback_form/email_subject.txt
feedback_form/templates/feedback_form/email_template.txt
feedback_form/templates/feedback_form/feedback.html
feedback_form/tests.py
feedback_form/urls.py
feedback_form/views.py
django_simple_feedback_form-2.0.1.dist-info/LICENSE.rst
django_simple_feedback_form-2.0.1.dist-info/WHEEL
django_simple_feedback_form-2.0.1.dist-info/METADATA
django_simple_feedback_form-2.0.1.dist-info/RECORD
